pytoken/__init__.py
pytoken/pytoken.py
pytoken-0.0.1.dist-info/METADATA
pytoken-0.0.1.dist-info/WHEEL
pytoken-0.0.1.dist-info/top_level.txt
pytoken-0.0.1.dist-info/RECORD
